pyfile/__init__.py
pymyfile/__init__.py
pymyfile-1.0.1.dist-info/LICENSE.txt
pymyfile-1.0.1.dist-info/METADATA
pymyfile-1.0.1.dist-info/WHEEL
pymyfile-1.0.1.dist-info/top_level.txt
pymyfile-1.0.1.dist-info/RECORD
