Metadata-Version: 2.1
Name: pymyfile
Version: 1.0.1
Summary: PyMyFile is a python library for advance file handeling in the easiest possible way
Home-page: https://github.com/Ankit404butfound/PyMyFile
Author: Ankit Raj Mahapatra
Author-email: ankitrajjitendra816@gmail.com
License: MIT
Download-URL: https://github.com/Ankit404butfound/PyMyFile/archive/1.0.0.tar.gz
Keywords: numpihy,denumiphy,bulletiphy,debulletiphy,asteriphy,deasteriphy,read
Platform: UNKNOWN
Classifier: Development Status :: 3 - Alpha
Classifier: Intended Audience :: Developers
Classifier: Topic :: Software Development :: Build Tools
Classifier: License :: OSI Approved :: MIT License
Classifier: Programming Language :: Python :: 3
Classifier: Programming Language :: Python :: 3.4
Classifier: Programming Language :: Python :: 3.5
Classifier: Programming Language :: Python :: 3.6
